src/gex/__init__.py
src/gex/__main__.py
src/gex/cli.py
src/gex/config.py
src/gex/logger.py
src/gex/util.py
gex_cli-1.0.4.dist-info/METADATA
gex_cli-1.0.4.dist-info/WHEEL
gex_cli-1.0.4.dist-info/entry_points.txt
gex_cli-1.0.4.dist-info/RECORD
