Metadata-Version: 2.1
Name: gex-cli
Version: 1.0.4
Summary: Command-line project generator using git repo.
Project-URL: Documentation, https://github.com/woidzero/gex-cli#readme
Project-URL: Issues, https://github.com/woidzero/gex-cli/issues
Project-URL: Source, https://github.com/woidzero/gex-cli
Project-URL: Chat, https://discord.gg/MhvDqCXAzP
Author-email: woidzero <woidzerov@gmail.com>
License-Expression: MIT
Keywords: cli,command-line,console,generator,project managment
Classifier: Development Status :: 5 - Production/Stable
Classifier: Environment :: Console
Classifier: License :: OSI Approved :: MIT License
Classifier: Operating System :: OS Independent
Classifier: Programming Language :: Python
Classifier: Programming Language :: Python :: 3.7
Classifier: Programming Language :: Python :: 3.8
Classifier: Programming Language :: Python :: 3.9
Classifier: Programming Language :: Python :: 3.10
Classifier: Programming Language :: Python :: 3.11
Classifier: Programming Language :: Python :: Implementation :: CPython
Classifier: Programming Language :: Python :: Implementation :: PyPy
Requires-Python: >=3.7
Requires-Dist: click
Requires-Dist: gitpython
Requires-Dist: mcfc
Requires-Dist: rich
